secretbutler/__init__.py
secretbutler-0.1.2.dist-info/METADATA
secretbutler-0.1.2.dist-info/WHEEL
secretbutler-0.1.2.dist-info/entry_points.txt
secretbutler-0.1.2.dist-info/licenses/LICENSE
secretbutler-0.1.2.dist-info/RECORD
