Metadata-Version: 2.4
Name: secretbutler
Version: 0.1.2
Summary: A local MCP server that manages API keys with user approval
Project-URL: Homepage, https://github.com/stillerman/SecretButler
Project-URL: Repository, https://github.com/stillerman/SecretButler
Project-URL: Issues, https://github.com/stillerman/SecretButler/issues
Author-email: Jason Stillerman <jason.t.stillerman@gmail.com>
License: MIT
License-File: LICENSE
Keywords: api-keys,mcp,secrets,security
Classifier: Development Status :: 4 - Beta
Classifier: Intended Audience :: Developers
Classifier: License :: OSI Approved :: MIT License
Classifier: Operating System :: MacOS
Classifier: Programming Language :: Python :: 3
Classifier: Programming Language :: Python :: 3.8
Classifier: Programming Language :: Python :: 3.9
Classifier: Programming Language :: Python :: 3.10
Classifier: Programming Language :: Python :: 3.11
Classifier: Programming Language :: Python :: 3.12
Classifier: Topic :: Security
Classifier: Topic :: Software Development :: Libraries :: Python Modules
Requires-Python: >=3.8
Requires-Dist: fastmcp
Requires-Dist: toml
